{
  "Iterations": {
    "Items": [
      {
        "StatsByStrategy": {
          "TestScriptExecutionsByStrategy": {},
          "TestScriptMillisByStrategy": {},
          "GenerationMicrosByStrategy": {},
          "TotalCandidatesByStrategy": {},
          "ValidCandidatesByStrategy": {},
          "AppliedCandidatesByStrategy": {}
        },
        "BeforeSize": 249,
        "AfterSize": 127,
        "SyntacticMillis": 6890,
        "SemanticMillis": 0
      },
      {
        "StatsByStrategy": {
          "TestScriptExecutionsByStrategy": {
            "ConstantPropagationReduction": 66,
            "EllipsisReduction": 6,
            "EmptyDeclarationReduction": 10,
            "LetReduction": 6,
            "ListReduction": 1,
            "LoopUnrollingReduction": 5,
            "PackageReduction": 1,
            "UnificationReduction": 10
          },
          "TestScriptMillisByStrategy": {
            "ConstantPropagationReduction": 9819,
            "EllipsisReduction": 894,
            "EmptyDeclarationReduction": 1476,
            "LetReduction": 911,
            "ListReduction": 154,
            "LoopUnrollingReduction": 747,
            "PackageReduction": 128,
            "UnificationReduction": 1489
          },
          "GenerationMicrosByStrategy": {
            "ConstantPropagationReduction": 13610,
            "EllipsisReduction": 1223,
            "EmptyDeclarationReduction": 1645,
            "IfReduction": 594,
            "ImportReduction": 108,
            "LetReduction": 1604,
            "ListReduction": 232,
            "LoopUnrollingReduction": 2034,
            "PackageReduction": 194,
            "RedundantNestingReduction": 147,
            "StringInterpolationReduction": 756,
            "TrivialIfReduction": 445,
            "UnificationReduction": 4104,
            "UnionReduction": 71
          },
          "TotalCandidatesByStrategy": {
            "ConstantPropagationReduction": 66,
            "EllipsisReduction": 6,
            "EmptyDeclarationReduction": 10,
            "IfReduction": 0,
            "ImportReduction": 0,
            "LetReduction": 6,
            "ListReduction": 1,
            "LoopUnrollingReduction": 5,
            "PackageReduction": 1,
            "RedundantNestingReduction": 0,
            "StringInterpolationReduction": 0,
            "TrivialIfReduction": 0,
            "UnificationReduction": 10,
            "UnionReduction": 0
          },
          "ValidCandidatesByStrategy": {
            "ConstantPropagationReduction": 36,
            "EllipsisReduction": 4,
            "EmptyDeclarationReduction": 10,
            "IfReduction": 0,
            "ImportReduction": 0,
            "LetReduction": 6,
            "ListReduction": 0,
            "LoopUnrollingReduction": 1,
            "PackageReduction": 0,
            "RedundantNestingReduction": 0,
            "StringInterpolationReduction": 0,
            "TrivialIfReduction": 0,
            "UnificationReduction": 10,
            "UnionReduction": 0
          },
          "AppliedCandidatesByStrategy": {
            "ConstantPropagationReduction": 9,
            "EllipsisReduction": 2,
            "EmptyDeclarationReduction": 4,
            "LetReduction": 3,
            "LoopUnrollingReduction": 1,
            "UnificationReduction": 4
          }
        },
        "BeforeSize": 127,
        "AfterSize": 90,
        "SyntacticMillis": 4058,
        "SemanticMillis": 15766
      },
      {
        "StatsByStrategy": {
          "TestScriptExecutionsByStrategy": {
            "ConstantPropagationReduction": 5,
            "EmptyDeclarationReduction": 15,
            "ListReduction": 1,
            "LoopUnrollingReduction": 2,
            "PackageReduction": 1
          },
          "TestScriptMillisByStrategy": {
            "ConstantPropagationReduction": 744,
            "EmptyDeclarationReduction": 2270,
            "ListReduction": 148,
            "LoopUnrollingReduction": 264,
            "PackageReduction": 127
          },
          "GenerationMicrosByStrategy": {
            "ConstantPropagationReduction": 749,
            "EllipsisReduction": 356,
            "EmptyDeclarationReduction": 2204,
            "IfReduction": 341,
            "ImportReduction": 54,
            "LetReduction": 136,
            "ListReduction": 128,
            "LoopUnrollingReduction": 471,
            "PackageReduction": 141,
            "RedundantNestingReduction": 150,
            "StringInterpolationReduction": 474,
            "TrivialIfReduction": 190,
            "UnificationReduction": 341,
            "UnionReduction": 70
          },
          "TotalCandidatesByStrategy": {
            "ConstantPropagationReduction": 5,
            "EllipsisReduction": 0,
            "EmptyDeclarationReduction": 15,
            "IfReduction": 0,
            "ImportReduction": 0,
            "LetReduction": 0,
            "ListReduction": 1,
            "LoopUnrollingReduction": 2,
            "PackageReduction": 1,
            "RedundantNestingReduction": 0,
            "StringInterpolationReduction": 0,
            "TrivialIfReduction": 0,
            "UnificationReduction": 0,
            "UnionReduction": 0
          },
          "ValidCandidatesByStrategy": {
            "ConstantPropagationReduction": 1,
            "EllipsisReduction": 0,
            "EmptyDeclarationReduction": 15,
            "IfReduction": 0,
            "ImportReduction": 0,
            "LetReduction": 0,
            "ListReduction": 0,
            "LoopUnrollingReduction": 0,
            "PackageReduction": 0,
            "RedundantNestingReduction": 0,
            "StringInterpolationReduction": 0,
            "TrivialIfReduction": 0,
            "UnificationReduction": 0,
            "UnionReduction": 0
          },
          "AppliedCandidatesByStrategy": {
            "ConstantPropagationReduction": 1,
            "EmptyDeclarationReduction": 5
          }
        },
        "BeforeSize": 90,
        "AfterSize": 75,
        "SyntacticMillis": 2943,
        "SemanticMillis": 3586
      },
      {
        "StatsByStrategy": {
          "TestScriptExecutionsByStrategy": {
            "ConstantPropagationReduction": 2,
            "ListReduction": 1,
            "LoopUnrollingReduction": 2,
            "PackageReduction": 1
          },
          "TestScriptMillisByStrategy": {
            "ConstantPropagationReduction": 298,
            "ListReduction": 147,
            "LoopUnrollingReduction": 280,
            "PackageReduction": 151
          },
          "GenerationMicrosByStrategy": {
            "ConstantPropagationReduction": 250,
            "EllipsisReduction": 71,
            "EmptyDeclarationReduction": 34,
            "IfReduction": 238,
            "ImportReduction": 41,
            "LetReduction": 108,
            "ListReduction": 98,
            "LoopUnrollingReduction": 421,
            "PackageReduction": 114,
            "RedundantNestingReduction": 116,
            "StringInterpolationReduction": 390,
            "TrivialIfReduction": 160,
            "UnificationReduction": 334,
            "UnionReduction": 48
          },
          "TotalCandidatesByStrategy": {
            "ConstantPropagationReduction": 2,
            "EllipsisReduction": 0,
            "EmptyDeclarationReduction": 0,
            "IfReduction": 0,
            "ImportReduction": 0,
            "LetReduction": 0,
            "ListReduction": 1,
            "LoopUnrollingReduction": 2,
            "PackageReduction": 1,
            "RedundantNestingReduction": 0,
            "StringInterpolationReduction": 0,
            "TrivialIfReduction": 0,
            "UnificationReduction": 0,
            "UnionReduction": 0
          },
          "ValidCandidatesByStrategy": {
            "ConstantPropagationReduction": 0,
            "EllipsisReduction": 0,
            "EmptyDeclarationReduction": 0,
            "IfReduction": 0,
            "ImportReduction": 0,
            "LetReduction": 0,
            "ListReduction": 0,
            "LoopUnrollingReduction": 0,
            "PackageReduction": 0,
            "RedundantNestingReduction": 0,
            "StringInterpolationReduction": 0,
            "TrivialIfReduction": 0,
            "UnificationReduction": 0,
            "UnionReduction": 0
          },
          "AppliedCandidatesByStrategy": {}
        },
        "BeforeSize": 75,
        "AfterSize": 75,
        "SyntacticMillis": 0,
        "SemanticMillis": 884
      }
    ]
  },
  "Total": {
    "StatsByStrategy": {
      "TestScriptExecutionsByStrategy": {
        "ConstantPropagationReduction": 73,
        "EllipsisReduction": 6,
        "EmptyDeclarationReduction": 25,
        "IfReduction": 0,
        "ImportReduction": 0,
        "LetReduction": 6,
        "ListReduction": 3,
        "LoopUnrollingReduction": 9,
        "PackageReduction": 3,
        "RedundantNestingReduction": 0,
        "StringInterpolationReduction": 0,
        "TrivialIfReduction": 0,
        "UnificationReduction": 10,
        "UnionReduction": 0
      },
      "TestScriptMillisByStrategy": {
        "ConstantPropagationReduction": 10861,
        "EllipsisReduction": 894,
        "EmptyDeclarationReduction": 3746,
        "IfReduction": 0,
        "ImportReduction": 0,
        "LetReduction": 911,
        "ListReduction": 449,
        "LoopUnrollingReduction": 1291,
        "PackageReduction": 406,
        "RedundantNestingReduction": 0,
        "StringInterpolationReduction": 0,
        "TrivialIfReduction": 0,
        "UnificationReduction": 1489,
        "UnionReduction": 0
      },
      "GenerationMicrosByStrategy": {
        "ConstantPropagationReduction": 14609,
        "EllipsisReduction": 1650,
        "EmptyDeclarationReduction": 3883,
        "IfReduction": 1173,
        "ImportReduction": 203,
        "LetReduction": 1848,
        "ListReduction": 458,
        "LoopUnrollingReduction": 2926,
        "PackageReduction": 449,
        "RedundantNestingReduction": 413,
        "StringInterpolationReduction": 1620,
        "TrivialIfReduction": 795,
        "UnificationReduction": 4779,
        "UnionReduction": 189
      },
      "TotalCandidatesByStrategy": {
        "ConstantPropagationReduction": 73,
        "EllipsisReduction": 6,
        "EmptyDeclarationReduction": 25,
        "IfReduction": 0,
        "ImportReduction": 0,
        "LetReduction": 6,
        "ListReduction": 3,
        "LoopUnrollingReduction": 9,
        "PackageReduction": 3,
        "RedundantNestingReduction": 0,
        "StringInterpolationReduction": 0,
        "TrivialIfReduction": 0,
        "UnificationReduction": 10,
        "UnionReduction": 0
      },
      "ValidCandidatesByStrategy": {
        "ConstantPropagationReduction": 37,
        "EllipsisReduction": 4,
        "EmptyDeclarationReduction": 25,
        "IfReduction": 0,
        "ImportReduction": 0,
        "LetReduction": 6,
        "ListReduction": 0,
        "LoopUnrollingReduction": 1,
        "PackageReduction": 0,
        "RedundantNestingReduction": 0,
        "StringInterpolationReduction": 0,
        "TrivialIfReduction": 0,
        "UnificationReduction": 10,
        "UnionReduction": 0
      },
      "AppliedCandidatesByStrategy": {
        "ConstantPropagationReduction": 10,
        "EllipsisReduction": 2,
        "EmptyDeclarationReduction": 9,
        "IfReduction": 0,
        "ImportReduction": 0,
        "LetReduction": 3,
        "ListReduction": 0,
        "LoopUnrollingReduction": 1,
        "PackageReduction": 0,
        "RedundantNestingReduction": 0,
        "StringInterpolationReduction": 0,
        "TrivialIfReduction": 0,
        "UnificationReduction": 4,
        "UnionReduction": 0
      }
    },
    "BeforeSize": 249,
    "AfterSize": 75,
    "SyntacticMillis": 13891,
    "SemanticMillis": 20236
  },
  "TotalTimeMillis": 34130,
  "TotalIterations": 4,
  "InputDir": "study/instances/extra/issue_2_inlined/final",
  "StartTime": "2024-10-24T21:55:01+02:00"
}