{
  "Iterations": {
    "Items": [
      {
        "StatsByStrategy": {
          "TestScriptExecutionsByStrategy": {},
          "TestScriptMillisByStrategy": {},
          "GenerationMicrosByStrategy": {},
          "TotalCandidatesByStrategy": {},
          "ValidCandidatesByStrategy": {},
          "AppliedCandidatesByStrategy": {}
        },
        "BeforeSize": 35,
        "AfterSize": 31,
        "SyntacticMillis": 1654,
        "SemanticMillis": 0
      },
      {
        "StatsByStrategy": {
          "TestScriptExecutionsByStrategy": {
            "ConstantPropagationReduction": 2,
            "EmptyDeclarationReduction": 1,
            "RedundantNestingReduction": 1,
            "TrivialIfReduction": 2,
            "UnionReduction": 2
          },
          "TestScriptMillisByStrategy": {
            "ConstantPropagationReduction": 257,
            "EmptyDeclarationReduction": 172,
            "RedundantNestingReduction": 129,
            "TrivialIfReduction": 265,
            "UnionReduction": 258
          },
          "GenerationMicrosByStrategy": {
            "ConstantPropagationReduction": 136,
            "EllipsisReduction": 34,
            "EmptyDeclarationReduction": 123,
            "IfReduction": 382,
            "ImportReduction": 97,
            "LetReduction": 96,
            "ListReduction": 80,
            "LoopUnrollingReduction": 273,
            "PackageReduction": 17,
            "RedundantNestingReduction": 63,
            "StringInterpolationReduction": 208,
            "TrivialIfReduction": 118,
            "UnificationReduction": 280,
            "UnionReduction": 106
          },
          "TotalCandidatesByStrategy": {
            "ConstantPropagationReduction": 2,
            "EllipsisReduction": 0,
            "EmptyDeclarationReduction": 1,
            "IfReduction": 0,
            "ImportReduction": 0,
            "LetReduction": 0,
            "ListReduction": 0,
            "LoopUnrollingReduction": 0,
            "PackageReduction": 0,
            "RedundantNestingReduction": 1,
            "StringInterpolationReduction": 0,
            "TrivialIfReduction": 2,
            "UnificationReduction": 0,
            "UnionReduction": 2
          },
          "ValidCandidatesByStrategy": {
            "ConstantPropagationReduction": 0,
            "EllipsisReduction": 0,
            "EmptyDeclarationReduction": 1,
            "IfReduction": 0,
            "ImportReduction": 0,
            "LetReduction": 0,
            "ListReduction": 0,
            "LoopUnrollingReduction": 0,
            "PackageReduction": 0,
            "RedundantNestingReduction": 0,
            "StringInterpolationReduction": 0,
            "TrivialIfReduction": 0,
            "UnificationReduction": 0,
            "UnionReduction": 0
          },
          "AppliedCandidatesByStrategy": {
            "EmptyDeclarationReduction": 1
          }
        },
        "BeforeSize": 31,
        "AfterSize": 30,
        "SyntacticMillis": 1188,
        "SemanticMillis": 1092
      },
      {
        "StatsByStrategy": {
          "TestScriptExecutionsByStrategy": {
            "ConstantPropagationReduction": 2,
            "RedundantNestingReduction": 1,
            "TrivialIfReduction": 2,
            "UnionReduction": 2
          },
          "TestScriptMillisByStrategy": {
            "ConstantPropagationReduction": 260,
            "RedundantNestingReduction": 162,
            "TrivialIfReduction": 265,
            "UnionReduction": 257
          },
          "GenerationMicrosByStrategy": {
            "ConstantPropagationReduction": 119,
            "EllipsisReduction": 38,
            "EmptyDeclarationReduction": 14,
            "IfReduction": 266,
            "ImportReduction": 126,
            "LetReduction": 128,
            "ListReduction": 105,
            "LoopUnrollingReduction": 85,
            "PackageReduction": 22,
            "RedundantNestingReduction": 75,
            "StringInterpolationReduction": 354,
            "TrivialIfReduction": 197,
            "UnificationReduction": 59,
            "UnionReduction": 165
          },
          "TotalCandidatesByStrategy": {
            "ConstantPropagationReduction": 2,
            "EllipsisReduction": 0,
            "EmptyDeclarationReduction": 0,
            "IfReduction": 0,
            "ImportReduction": 0,
            "LetReduction": 0,
            "ListReduction": 0,
            "LoopUnrollingReduction": 0,
            "PackageReduction": 0,
            "RedundantNestingReduction": 1,
            "StringInterpolationReduction": 0,
            "TrivialIfReduction": 2,
            "UnificationReduction": 0,
            "UnionReduction": 2
          },
          "ValidCandidatesByStrategy": {
            "ConstantPropagationReduction": 0,
            "EllipsisReduction": 0,
            "EmptyDeclarationReduction": 0,
            "IfReduction": 0,
            "ImportReduction": 0,
            "LetReduction": 0,
            "ListReduction": 0,
            "LoopUnrollingReduction": 0,
            "PackageReduction": 0,
            "RedundantNestingReduction": 0,
            "StringInterpolationReduction": 0,
            "TrivialIfReduction": 0,
            "UnificationReduction": 0,
            "UnionReduction": 0
          },
          "AppliedCandidatesByStrategy": {}
        },
        "BeforeSize": 30,
        "AfterSize": 30,
        "SyntacticMillis": 0,
        "SemanticMillis": 954
      }
    ]
  },
  "Total": {
    "StatsByStrategy": {
      "TestScriptExecutionsByStrategy": {
        "ConstantPropagationReduction": 4,
        "EllipsisReduction": 0,
        "EmptyDeclarationReduction": 1,
        "IfReduction": 0,
        "ImportReduction": 0,
        "LetReduction": 0,
        "ListReduction": 0,
        "LoopUnrollingReduction": 0,
        "PackageReduction": 0,
        "RedundantNestingReduction": 2,
        "StringInterpolationReduction": 0,
        "TrivialIfReduction": 4,
        "UnificationReduction": 0,
        "UnionReduction": 4
      },
      "TestScriptMillisByStrategy": {
        "ConstantPropagationReduction": 517,
        "EllipsisReduction": 0,
        "EmptyDeclarationReduction": 172,
        "IfReduction": 0,
        "ImportReduction": 0,
        "LetReduction": 0,
        "ListReduction": 0,
        "LoopUnrollingReduction": 0,
        "PackageReduction": 0,
        "RedundantNestingReduction": 291,
        "StringInterpolationReduction": 0,
        "TrivialIfReduction": 530,
        "UnificationReduction": 0,
        "UnionReduction": 515
      },
      "GenerationMicrosByStrategy": {
        "ConstantPropagationReduction": 255,
        "EllipsisReduction": 72,
        "EmptyDeclarationReduction": 137,
        "IfReduction": 648,
        "ImportReduction": 223,
        "LetReduction": 224,
        "ListReduction": 185,
        "LoopUnrollingReduction": 358,
        "PackageReduction": 39,
        "RedundantNestingReduction": 138,
        "StringInterpolationReduction": 562,
        "TrivialIfReduction": 315,
        "UnificationReduction": 339,
        "UnionReduction": 271
      },
      "TotalCandidatesByStrategy": {
        "ConstantPropagationReduction": 4,
        "EllipsisReduction": 0,
        "EmptyDeclarationReduction": 1,
        "IfReduction": 0,
        "ImportReduction": 0,
        "LetReduction": 0,
        "ListReduction": 0,
        "LoopUnrollingReduction": 0,
        "PackageReduction": 0,
        "RedundantNestingReduction": 2,
        "StringInterpolationReduction": 0,
        "TrivialIfReduction": 4,
        "UnificationReduction": 0,
        "UnionReduction": 4
      },
      "ValidCandidatesByStrategy": {
        "ConstantPropagationReduction": 0,
        "EllipsisReduction": 0,
        "EmptyDeclarationReduction": 1,
        "IfReduction": 0,
        "ImportReduction": 0,
        "LetReduction": 0,
        "ListReduction": 0,
        "LoopUnrollingReduction": 0,
        "PackageReduction": 0,
        "RedundantNestingReduction": 0,
        "StringInterpolationReduction": 0,
        "TrivialIfReduction": 0,
        "UnificationReduction": 0,
        "UnionReduction": 0
      },
      "AppliedCandidatesByStrategy": {
        "ConstantPropagationReduction": 0,
        "EllipsisReduction": 0,
        "EmptyDeclarationReduction": 1,
        "IfReduction": 0,
        "ImportReduction": 0,
        "LetReduction": 0,
        "ListReduction": 0,
        "LoopUnrollingReduction": 0,
        "PackageReduction": 0,
        "RedundantNestingReduction": 0,
        "StringInterpolationReduction": 0,
        "TrivialIfReduction": 0,
        "UnificationReduction": 0,
        "UnionReduction": 0
      }
    },
    "BeforeSize": 35,
    "AfterSize": 30,
    "SyntacticMillis": 2842,
    "SemanticMillis": 2046
  },
  "TotalTimeMillis": 4889,
  "TotalIterations": 3,
  "InputDir": "study/instances/error/issue_2473/final",
  "StartTime": "2024-10-25T23:08:06+02:00"
}