{
  "Iterations": {
    "Items": [
      {
        "StatsByStrategy": {
          "TestScriptExecutionsByStrategy": {},
          "TestScriptMillisByStrategy": {},
          "GenerationMicrosByStrategy": {},
          "TotalCandidatesByStrategy": {},
          "ValidCandidatesByStrategy": {},
          "AppliedCandidatesByStrategy": {}
        },
        "BeforeSize": 251,
        "AfterSize": 53,
        "SyntacticMillis": 6388,
        "SemanticMillis": 0
      },
      {
        "StatsByStrategy": {
          "TestScriptExecutionsByStrategy": {
            "LoopUnrollingReduction": 1
          },
          "TestScriptMillisByStrategy": {
            "LoopUnrollingReduction": 202
          },
          "GenerationMicrosByStrategy": {
            "LoopUnrollingReduction": 532
          },
          "TotalCandidatesByStrategy": {
            "LoopUnrollingReduction": 1
          },
          "ValidCandidatesByStrategy": {
            "LoopUnrollingReduction": 0
          },
          "AppliedCandidatesByStrategy": {}
        },
        "BeforeSize": 53,
        "AfterSize": 53,
        "SyntacticMillis": 0,
        "SemanticMillis": 203
      }
    ]
  },
  "Total": {
    "StatsByStrategy": {
      "TestScriptExecutionsByStrategy": {
        "ConstantPropagationReduction": 0,
        "EllipsisReduction": 0,
        "EmptyDeclarationReduction": 0,
        "IfReduction": 0,
        "ImportReduction": 0,
        "LetReduction": 0,
        "ListReduction": 0,
        "LoopUnrollingReduction": 1,
        "PackageReduction": 0,
        "RedundantNestingReduction": 0,
        "StringInterpolationReduction": 0,
        "TrivialIfReduction": 0,
        "UnificationReduction": 0,
        "UnionReduction": 0
      },
      "TestScriptMillisByStrategy": {
        "ConstantPropagationReduction": 0,
        "EllipsisReduction": 0,
        "EmptyDeclarationReduction": 0,
        "IfReduction": 0,
        "ImportReduction": 0,
        "LetReduction": 0,
        "ListReduction": 0,
        "LoopUnrollingReduction": 202,
        "PackageReduction": 0,
        "RedundantNestingReduction": 0,
        "StringInterpolationReduction": 0,
        "TrivialIfReduction": 0,
        "UnificationReduction": 0,
        "UnionReduction": 0
      },
      "GenerationMicrosByStrategy": {
        "ConstantPropagationReduction": 0,
        "EllipsisReduction": 0,
        "EmptyDeclarationReduction": 0,
        "IfReduction": 0,
        "ImportReduction": 0,
        "LetReduction": 0,
        "ListReduction": 0,
        "LoopUnrollingReduction": 532,
        "PackageReduction": 0,
        "RedundantNestingReduction": 0,
        "StringInterpolationReduction": 0,
        "TrivialIfReduction": 0,
        "UnificationReduction": 0,
        "UnionReduction": 0
      },
      "TotalCandidatesByStrategy": {
        "ConstantPropagationReduction": 0,
        "EllipsisReduction": 0,
        "EmptyDeclarationReduction": 0,
        "IfReduction": 0,
        "ImportReduction": 0,
        "LetReduction": 0,
        "ListReduction": 0,
        "LoopUnrollingReduction": 1,
        "PackageReduction": 0,
        "RedundantNestingReduction": 0,
        "StringInterpolationReduction": 0,
        "TrivialIfReduction": 0,
        "UnificationReduction": 0,
        "UnionReduction": 0
      },
      "ValidCandidatesByStrategy": {
        "ConstantPropagationReduction": 0,
        "EllipsisReduction": 0,
        "EmptyDeclarationReduction": 0,
        "IfReduction": 0,
        "ImportReduction": 0,
        "LetReduction": 0,
        "ListReduction": 0,
        "LoopUnrollingReduction": 0,
        "PackageReduction": 0,
        "RedundantNestingReduction": 0,
        "StringInterpolationReduction": 0,
        "TrivialIfReduction": 0,
        "UnificationReduction": 0,
        "UnionReduction": 0
      },
      "AppliedCandidatesByStrategy": {
        "ConstantPropagationReduction": 0,
        "EllipsisReduction": 0,
        "EmptyDeclarationReduction": 0,
        "IfReduction": 0,
        "ImportReduction": 0,
        "LetReduction": 0,
        "ListReduction": 0,
        "LoopUnrollingReduction": 0,
        "PackageReduction": 0,
        "RedundantNestingReduction": 0,
        "StringInterpolationReduction": 0,
        "TrivialIfReduction": 0,
        "UnificationReduction": 0,
        "UnionReduction": 0
      }
    },
    "BeforeSize": 251,
    "AfterSize": 53,
    "SyntacticMillis": 6388,
    "SemanticMillis": 203
  },
  "TotalTimeMillis": 6592,
  "TotalIterations": 2,
  "InputDir": "study/instances/panic/issue_2584/v1",
  "StartTime": "2024-11-01T14:48:59+01:00"
}