{
  "Iterations": {
    "Items": [
      {
        "StatsByStrategy": {
          "TestScriptExecutionsByStrategy": {},
          "TestScriptMillisByStrategy": {},
          "GenerationMicrosByStrategy": {},
          "TotalCandidatesByStrategy": {},
          "ValidCandidatesByStrategy": {},
          "AppliedCandidatesByStrategy": {}
        },
        "BeforeSize": 124,
        "AfterSize": 100,
        "SyntacticMillis": 6342,
        "SemanticMillis": 0
      },
      {
        "StatsByStrategy": {
          "TestScriptExecutionsByStrategy": {
            "UnionReduction": 6
          },
          "TestScriptMillisByStrategy": {
            "UnionReduction": 819
          },
          "GenerationMicrosByStrategy": {
            "UnionReduction": 662
          },
          "TotalCandidatesByStrategy": {
            "UnionReduction": 6
          },
          "ValidCandidatesByStrategy": {
            "UnionReduction": 0
          },
          "AppliedCandidatesByStrategy": {}
        },
        "BeforeSize": 100,
        "AfterSize": 100,
        "SyntacticMillis": 0,
        "SemanticMillis": 827
      }
    ]
  },
  "Total": {
    "StatsByStrategy": {
      "TestScriptExecutionsByStrategy": {
        "ConstantPropagationReduction": 0,
        "EllipsisReduction": 0,
        "EmptyDeclarationReduction": 0,
        "IfReduction": 0,
        "ImportReduction": 0,
        "LetReduction": 0,
        "ListReduction": 0,
        "LoopUnrollingReduction": 0,
        "PackageReduction": 0,
        "RedundantNestingReduction": 0,
        "StringInterpolationReduction": 0,
        "TrivialIfReduction": 0,
        "UnificationReduction": 0,
        "UnionReduction": 6
      },
      "TestScriptMillisByStrategy": {
        "ConstantPropagationReduction": 0,
        "EllipsisReduction": 0,
        "EmptyDeclarationReduction": 0,
        "IfReduction": 0,
        "ImportReduction": 0,
        "LetReduction": 0,
        "ListReduction": 0,
        "LoopUnrollingReduction": 0,
        "PackageReduction": 0,
        "RedundantNestingReduction": 0,
        "StringInterpolationReduction": 0,
        "TrivialIfReduction": 0,
        "UnificationReduction": 0,
        "UnionReduction": 819
      },
      "GenerationMicrosByStrategy": {
        "ConstantPropagationReduction": 0,
        "EllipsisReduction": 0,
        "EmptyDeclarationReduction": 0,
        "IfReduction": 0,
        "ImportReduction": 0,
        "LetReduction": 0,
        "ListReduction": 0,
        "LoopUnrollingReduction": 0,
        "PackageReduction": 0,
        "RedundantNestingReduction": 0,
        "StringInterpolationReduction": 0,
        "TrivialIfReduction": 0,
        "UnificationReduction": 0,
        "UnionReduction": 662
      },
      "TotalCandidatesByStrategy": {
        "ConstantPropagationReduction": 0,
        "EllipsisReduction": 0,
        "EmptyDeclarationReduction": 0,
        "IfReduction": 0,
        "ImportReduction": 0,
        "LetReduction": 0,
        "ListReduction": 0,
        "LoopUnrollingReduction": 0,
        "PackageReduction": 0,
        "RedundantNestingReduction": 0,
        "StringInterpolationReduction": 0,
        "TrivialIfReduction": 0,
        "UnificationReduction": 0,
        "UnionReduction": 6
      },
      "ValidCandidatesByStrategy": {
        "ConstantPropagationReduction": 0,
        "EllipsisReduction": 0,
        "EmptyDeclarationReduction": 0,
        "IfReduction": 0,
        "ImportReduction": 0,
        "LetReduction": 0,
        "ListReduction": 0,
        "LoopUnrollingReduction": 0,
        "PackageReduction": 0,
        "RedundantNestingReduction": 0,
        "StringInterpolationReduction": 0,
        "TrivialIfReduction": 0,
        "UnificationReduction": 0,
        "UnionReduction": 0
      },
      "AppliedCandidatesByStrategy": {
        "ConstantPropagationReduction": 0,
        "EllipsisReduction": 0,
        "EmptyDeclarationReduction": 0,
        "IfReduction": 0,
        "ImportReduction": 0,
        "LetReduction": 0,
        "ListReduction": 0,
        "LoopUnrollingReduction": 0,
        "PackageReduction": 0,
        "RedundantNestingReduction": 0,
        "StringInterpolationReduction": 0,
        "TrivialIfReduction": 0,
        "UnificationReduction": 0,
        "UnionReduction": 0
      }
    },
    "BeforeSize": 124,
    "AfterSize": 100,
    "SyntacticMillis": 6342,
    "SemanticMillis": 827
  },
  "TotalTimeMillis": 7169,
  "TotalIterations": 2,
  "InputDir": "study/instances/error/issue_2209/final",
  "StartTime": "2024-11-01T15:13:15+01:00"
}