{
  "Iterations": {
    "Items": [
      {
        "StatsByStrategy": {
          "TestScriptExecutionsByStrategy": {},
          "TestScriptMillisByStrategy": {},
          "GenerationMicrosByStrategy": {},
          "TotalCandidatesByStrategy": {},
          "ValidCandidatesByStrategy": {},
          "AppliedCandidatesByStrategy": {}
        },
        "BeforeSize": 39,
        "AfterSize": 32,
        "SyntacticMillis": 1793,
        "SemanticMillis": 0
      },
      {
        "StatsByStrategy": {
          "TestScriptExecutionsByStrategy": {
            "ConstantPropagationReduction": 3,
            "LetReduction": 1,
            "LoopUnrollingReduction": 1
          },
          "TestScriptMillisByStrategy": {
            "ConstantPropagationReduction": 399,
            "LetReduction": 166,
            "LoopUnrollingReduction": 125
          },
          "GenerationMicrosByStrategy": {
            "ConstantPropagationReduction": 248,
            "EllipsisReduction": 34,
            "EmptyDeclarationReduction": 78,
            "IfReduction": 289,
            "ImportReduction": 26,
            "LetReduction": 152,
            "ListReduction": 17,
            "LoopUnrollingReduction": 686,
            "PackageReduction": 21,
            "RedundantNestingReduction": 19,
            "StringInterpolationReduction": 270,
            "TrivialIfReduction": 31,
            "UnificationReduction": 262,
            "UnionReduction": 27
          },
          "TotalCandidatesByStrategy": {
            "ConstantPropagationReduction": 3,
            "EllipsisReduction": 0,
            "EmptyDeclarationReduction": 0,
            "IfReduction": 0,
            "ImportReduction": 0,
            "LetReduction": 1,
            "ListReduction": 0,
            "LoopUnrollingReduction": 1,
            "PackageReduction": 0,
            "RedundantNestingReduction": 0,
            "StringInterpolationReduction": 0,
            "TrivialIfReduction": 0,
            "UnificationReduction": 0,
            "UnionReduction": 0
          },
          "ValidCandidatesByStrategy": {
            "ConstantPropagationReduction": 1,
            "EllipsisReduction": 0,
            "EmptyDeclarationReduction": 0,
            "IfReduction": 0,
            "ImportReduction": 0,
            "LetReduction": 0,
            "ListReduction": 0,
            "LoopUnrollingReduction": 0,
            "PackageReduction": 0,
            "RedundantNestingReduction": 0,
            "StringInterpolationReduction": 0,
            "TrivialIfReduction": 0,
            "UnificationReduction": 0,
            "UnionReduction": 0
          },
          "AppliedCandidatesByStrategy": {
            "ConstantPropagationReduction": 1
          }
        },
        "BeforeSize": 32,
        "AfterSize": 31,
        "SyntacticMillis": 1363,
        "SemanticMillis": 698
      },
      {
        "StatsByStrategy": {
          "TestScriptExecutionsByStrategy": {
            "ConstantPropagationReduction": 1,
            "EmptyDeclarationReduction": 1,
            "LetReduction": 1,
            "LoopUnrollingReduction": 1
          },
          "TestScriptMillisByStrategy": {
            "ConstantPropagationReduction": 126,
            "EmptyDeclarationReduction": 150,
            "LetReduction": 155,
            "LoopUnrollingReduction": 123
          },
          "GenerationMicrosByStrategy": {
            "ConstantPropagationReduction": 73,
            "EllipsisReduction": 51,
            "EmptyDeclarationReduction": 222,
            "IfReduction": 165,
            "ImportReduction": 21,
            "LetReduction": 153,
            "ListReduction": 22,
            "LoopUnrollingReduction": 219,
            "PackageReduction": 16,
            "RedundantNestingReduction": 28,
            "StringInterpolationReduction": 341,
            "TrivialIfReduction": 42,
            "UnificationReduction": 190,
            "UnionReduction": 26
          },
          "TotalCandidatesByStrategy": {
            "ConstantPropagationReduction": 1,
            "EllipsisReduction": 0,
            "EmptyDeclarationReduction": 1,
            "IfReduction": 0,
            "ImportReduction": 0,
            "LetReduction": 1,
            "ListReduction": 0,
            "LoopUnrollingReduction": 1,
            "PackageReduction": 0,
            "RedundantNestingReduction": 0,
            "StringInterpolationReduction": 0,
            "TrivialIfReduction": 0,
            "UnificationReduction": 0,
            "UnionReduction": 0
          },
          "ValidCandidatesByStrategy": {
            "ConstantPropagationReduction": 0,
            "EllipsisReduction": 0,
            "EmptyDeclarationReduction": 1,
            "IfReduction": 0,
            "ImportReduction": 0,
            "LetReduction": 0,
            "ListReduction": 0,
            "LoopUnrollingReduction": 0,
            "PackageReduction": 0,
            "RedundantNestingReduction": 0,
            "StringInterpolationReduction": 0,
            "TrivialIfReduction": 0,
            "UnificationReduction": 0,
            "UnionReduction": 0
          },
          "AppliedCandidatesByStrategy": {
            "EmptyDeclarationReduction": 1
          }
        },
        "BeforeSize": 31,
        "AfterSize": 29,
        "SyntacticMillis": 1127,
        "SemanticMillis": 561
      },
      {
        "StatsByStrategy": {
          "TestScriptExecutionsByStrategy": {
            "ConstantPropagationReduction": 1,
            "LetReduction": 1,
            "LoopUnrollingReduction": 1
          },
          "TestScriptMillisByStrategy": {
            "ConstantPropagationReduction": 127,
            "LetReduction": 162,
            "LoopUnrollingReduction": 123
          },
          "GenerationMicrosByStrategy": {
            "ConstantPropagationReduction": 67,
            "EllipsisReduction": 28,
            "EmptyDeclarationReduction": 80,
            "IfReduction": 135,
            "ImportReduction": 15,
            "LetReduction": 108,
            "ListReduction": 12,
            "LoopUnrollingReduction": 220,
            "PackageReduction": 17,
            "RedundantNestingReduction": 17,
            "StringInterpolationReduction": 306,
            "TrivialIfReduction": 30,
            "UnificationReduction": 191,
            "UnionReduction": 17
          },
          "TotalCandidatesByStrategy": {
            "ConstantPropagationReduction": 1,
            "EllipsisReduction": 0,
            "EmptyDeclarationReduction": 0,
            "IfReduction": 0,
            "ImportReduction": 0,
            "LetReduction": 1,
            "ListReduction": 0,
            "LoopUnrollingReduction": 1,
            "PackageReduction": 0,
            "RedundantNestingReduction": 0,
            "StringInterpolationReduction": 0,
            "TrivialIfReduction": 0,
            "UnificationReduction": 0,
            "UnionReduction": 0
          },
          "ValidCandidatesByStrategy": {
            "ConstantPropagationReduction": 0,
            "EllipsisReduction": 0,
            "EmptyDeclarationReduction": 0,
            "IfReduction": 0,
            "ImportReduction": 0,
            "LetReduction": 0,
            "ListReduction": 0,
            "LoopUnrollingReduction": 0,
            "PackageReduction": 0,
            "RedundantNestingReduction": 0,
            "StringInterpolationReduction": 0,
            "TrivialIfReduction": 0,
            "UnificationReduction": 0,
            "UnionReduction": 0
          },
          "AppliedCandidatesByStrategy": {}
        },
        "BeforeSize": 29,
        "AfterSize": 29,
        "SyntacticMillis": 0,
        "SemanticMillis": 415
      }
    ]
  },
  "Total": {
    "StatsByStrategy": {
      "TestScriptExecutionsByStrategy": {
        "ConstantPropagationReduction": 5,
        "EllipsisReduction": 0,
        "EmptyDeclarationReduction": 1,
        "IfReduction": 0,
        "ImportReduction": 0,
        "LetReduction": 3,
        "ListReduction": 0,
        "LoopUnrollingReduction": 3,
        "PackageReduction": 0,
        "RedundantNestingReduction": 0,
        "StringInterpolationReduction": 0,
        "TrivialIfReduction": 0,
        "UnificationReduction": 0,
        "UnionReduction": 0
      },
      "TestScriptMillisByStrategy": {
        "ConstantPropagationReduction": 652,
        "EllipsisReduction": 0,
        "EmptyDeclarationReduction": 150,
        "IfReduction": 0,
        "ImportReduction": 0,
        "LetReduction": 483,
        "ListReduction": 0,
        "LoopUnrollingReduction": 371,
        "PackageReduction": 0,
        "RedundantNestingReduction": 0,
        "StringInterpolationReduction": 0,
        "TrivialIfReduction": 0,
        "UnificationReduction": 0,
        "UnionReduction": 0
      },
      "GenerationMicrosByStrategy": {
        "ConstantPropagationReduction": 388,
        "EllipsisReduction": 113,
        "EmptyDeclarationReduction": 380,
        "IfReduction": 589,
        "ImportReduction": 62,
        "LetReduction": 413,
        "ListReduction": 51,
        "LoopUnrollingReduction": 1125,
        "PackageReduction": 54,
        "RedundantNestingReduction": 64,
        "StringInterpolationReduction": 917,
        "TrivialIfReduction": 103,
        "UnificationReduction": 643,
        "UnionReduction": 70
      },
      "TotalCandidatesByStrategy": {
        "ConstantPropagationReduction": 5,
        "EllipsisReduction": 0,
        "EmptyDeclarationReduction": 1,
        "IfReduction": 0,
        "ImportReduction": 0,
        "LetReduction": 3,
        "ListReduction": 0,
        "LoopUnrollingReduction": 3,
        "PackageReduction": 0,
        "RedundantNestingReduction": 0,
        "StringInterpolationReduction": 0,
        "TrivialIfReduction": 0,
        "UnificationReduction": 0,
        "UnionReduction": 0
      },
      "ValidCandidatesByStrategy": {
        "ConstantPropagationReduction": 1,
        "EllipsisReduction": 0,
        "EmptyDeclarationReduction": 1,
        "IfReduction": 0,
        "ImportReduction": 0,
        "LetReduction": 0,
        "ListReduction": 0,
        "LoopUnrollingReduction": 0,
        "PackageReduction": 0,
        "RedundantNestingReduction": 0,
        "StringInterpolationReduction": 0,
        "TrivialIfReduction": 0,
        "UnificationReduction": 0,
        "UnionReduction": 0
      },
      "AppliedCandidatesByStrategy": {
        "ConstantPropagationReduction": 1,
        "EllipsisReduction": 0,
        "EmptyDeclarationReduction": 1,
        "IfReduction": 0,
        "ImportReduction": 0,
        "LetReduction": 0,
        "ListReduction": 0,
        "LoopUnrollingReduction": 0,
        "PackageReduction": 0,
        "RedundantNestingReduction": 0,
        "StringInterpolationReduction": 0,
        "TrivialIfReduction": 0,
        "UnificationReduction": 0,
        "UnionReduction": 0
      }
    },
    "BeforeSize": 39,
    "AfterSize": 29,
    "SyntacticMillis": 4283,
    "SemanticMillis": 1674
  },
  "TotalTimeMillis": 5961,
  "TotalIterations": 4,
  "InputDir": "study/instances/semantic/issue_2218/v2",
  "StartTime": "2024-10-24T22:05:54+02:00"
}